kube_authkit/__init__.py
kube_authkit/config.py
kube_authkit/exceptions.py
kube_authkit/factory.py
kube_authkit/strategies/__init__.py
kube_authkit/strategies/base.py
kube_authkit/strategies/incluster.py
kube_authkit/strategies/kubeconfig.py
kube_authkit/strategies/oidc.py
kube_authkit/strategies/openshift.py
kube_authkit-0.2.0.dist-info/METADATA
kube_authkit-0.2.0.dist-info/WHEEL
kube_authkit-0.2.0.dist-info/licenses/LICENSE
kube_authkit-0.2.0.dist-info/RECORD
