Metadata-Version: 2.4
Name: kube-authkit
Version: 0.2.0
Summary: Unified Kubernetes authentication toolkit - supports KubeConfig, In-Cluster, OIDC, and OpenShift OAuth authentication
Project-URL: Homepage, https://github.com/kube-authkit/kube-authkit
Project-URL: Documentation, https://github.com/kube-authkit/kube-authkit#readme
Project-URL: Repository, https://github.com/kube-authkit/kube-authkit
Project-URL: Issues, https://github.com/kube-authkit/kube-authkit/issues
Author: Kube AuthKit Contributors
License: Apache-2.0
License-File: LICENSE
Keywords: authentication,k8s,kubeconfig,kubernetes,oauth,oidc,openshift
Classifier: Development Status :: 3 - Alpha
Classifier: Intended Audience :: Developers
Classifier: License :: OSI Approved :: Apache Software License
Classifier: Programming Language :: Python :: 3
Classifier: Programming Language :: Python :: 3.10
Classifier: Programming Language :: Python :: 3.11
Classifier: Programming Language :: Python :: 3.12
Classifier: Topic :: Software Development :: Libraries :: Python Modules
Classifier: Topic :: System :: Systems Administration :: Authentication/Directory
Requires-Python: >=3.10
Requires-Dist: kubernetes>=27.2.0
Requires-Dist: pyjwt>=2.8.0
Requires-Dist: requests>=2.31.0
Requires-Dist: urllib3>=2.6.0
Provides-Extra: dev
Requires-Dist: pytest-cov>=4.1.0; extra == 'dev'
Requires-Dist: pytest-mock>=3.11.1; extra == 'dev'
Requires-Dist: pytest>=7.4.0; extra == 'dev'
Requires-Dist: ruff>=0.1.0; extra == 'dev'
Provides-Extra: keyring
Requires-Dist: keyring>=24.0.0; extra == 'keyring'
